cli/__init__.py
cli/main.py
neuronum-12.0.1.dist-info/licenses/LICENSE.md
neuronum-12.0.1.dist-info/METADATA
neuronum-12.0.1.dist-info/WHEEL
neuronum-12.0.1.dist-info/entry_points.txt
neuronum-12.0.1.dist-info/top_level.txt
neuronum-12.0.1.dist-info/RECORD
