Metadata-Version: 2.4
Name: neuronum
Version: 12.0.1
Summary: Official Neuronum Tools Library
Home-page: https://neuronum.net
Author: Neuronum Cybernetics
Author-email: welcome@neuronum.net
Project-URL: GitHub, https://github.com/neuronumcybernetics/neuronum
Classifier: Programming Language :: Python :: 3
Classifier: License :: OSI Approved :: MIT License
Classifier: Operating System :: OS Independent
Requires-Python: >=3.8
License-File: LICENSE.md
Requires-Dist: aiohttp
Requires-Dist: aiofiles
Requires-Dist: websockets
Requires-Dist: click
Requires-Dist: questionary
Requires-Dist: python-dotenv
Requires-Dist: requests
Requires-Dist: cryptography
Requires-Dist: bip_utils
Dynamic: author
Dynamic: author-email
Dynamic: classifier
Dynamic: description
Dynamic: description-content-type
Dynamic: home-page
Dynamic: license-file
Dynamic: project-url
Dynamic: requires-dist
Dynamic: requires-python
Dynamic: summary
